[
  {
    "name": "configQuiz",
    "path": "/configQuiz",
    "component": "C:\\\\Users\\\\Ana Júlia Lins\\\\Desktop\\\\Linkedin\\\\quest game\\\\quest-app\\\\pages\\\\configQuiz.vue",
    "chunkName": "pages/configQuiz",
    "_name": "_a4f3db9c"
  },
  {
    "name": "dashboard",
    "path": "/dashboard",
    "component": "C:\\\\Users\\\\Ana Júlia Lins\\\\Desktop\\\\Linkedin\\\\quest game\\\\quest-app\\\\pages\\\\dashboard.vue",
    "chunkName": "pages/dashboard",
    "_name": "_5797f069"
  },
  {
    "name": "login",
    "path": "/login",
    "component": "C:\\\\Users\\\\Ana Júlia Lins\\\\Desktop\\\\Linkedin\\\\quest game\\\\quest-app\\\\pages\\\\login.vue",
    "chunkName": "pages/login",
    "_name": "_350ca93e"
  },
  {
    "name": "quests",
    "path": "/quests",
    "component": "C:\\\\Users\\\\Ana Júlia Lins\\\\Desktop\\\\Linkedin\\\\quest game\\\\quest-app\\\\pages\\\\quests.vue",
    "chunkName": "pages/quests",
    "_name": "_0a920c68"
  },
  {
    "name": "register",
    "path": "/register",
    "component": "C:\\\\Users\\\\Ana Júlia Lins\\\\Desktop\\\\Linkedin\\\\quest game\\\\quest-app\\\\pages\\\\register.vue",
    "chunkName": "pages/register",
    "_name": "_2ab3fede"
  },
  {
    "name": "userInfo",
    "path": "/userInfo",
    "component": "C:\\\\Users\\\\Ana Júlia Lins\\\\Desktop\\\\Linkedin\\\\quest game\\\\quest-app\\\\pages\\\\userInfo.vue",
    "chunkName": "pages/userInfo",
    "_name": "_6d538c54"
  }
]
